README
setup.py
mrg_utils/__init__.py
mrg_utils/mrg_utils.py
mrg_utils/mrg_utils_driver.py
mrg_utils.egg-info/PKG-INFO
mrg_utils.egg-info/SOURCES.txt
mrg_utils.egg-info/dependency_links.txt
mrg_utils.egg-info/top_level.txt
mrg_utils/cuecorp/__init__.py
mrg_utils/docNode/__init__.py
mrg_utils/headRules/__init__.py
mrg_utils/mrg_document/__init__.py
mrg_utils/node/__init__.py
mrg_utils/nonTerminalNode/__init__.py
mrg_utils/rootNode/__init__.py
mrg_utils/sentence/__init__.py
mrg_utils/sexpr_parse/__init__.py
mrg_utils/terminalNode/__init__.py