Metadata-Version: 1.0
Name: mrg-utils
Version: 0.0.1
Summary: A set of utilities for interacting with Penn-Treebank .mrg-formatted parses and identifying syntactic heads
Home-page: https://github.com/relwell/mrg_utils
Author: Robert Elwell
Author-email: robert.elwell@gmail.com
License: GPL
Platform: UNKNOWN
